{
  "modulo": "Módulo Específico: Sector Frutas, verduras y derivados",
  "imagenEncabezado": "img/comunes/logo.svg",
  "contenido": [
    {
      "titulo": "Portada",
      "fondo": "img/comunes/portada.svg",
      "subclase": "portada"
    },
    {
      "titulo": "Introducción",
      "fondo": "img/modFru/greengrocers.jpg",
      "contenido": [
        {
          "clase": "texto",
          "subclase": "recuadro",
          "animacion": "fadeInRight",
          "texto": "Hasta ahora en los módulos anteriores has visto todo lo relacionado con la Higiene y Seguridad Alimentaria de forma amplia, pero genérica.<br><br>En este Módulo vas a poder ampliar la información vista anteriormente pero enfocada exclusivamente al Sector de las Frutas y Hortalizas, desde las alteraciones más comunes que sufren estos productos hasta los peligros más específicos, como pueden ser ciertos contaminantes químicos."
        }
      ]
    },
    {
      "titulo": "Definiciones",
      "contenido": [
        {
          "clase": "icono",
          "animacion": "fadeInRight",
          "subclase": "definicion",
          "texto": "<b>Definiciones:</b><br>A continuación vamos a ver la definición de hortalizas, verduras, legumbres, frutas y setas."
        },
        {
          "clase": "tabs",
          "animacion": "fadeInRight",
          "contenido": [
            {
              "titulo": "Hortalizas",
              "texto": "Toda planta herbácea que se cultiva y que es adecuada para el consumo, bien cruda o bien cocinada. El término </b>verdura</b> hace referencia a los órganos verdes de dichas plantas, especialmente hojas, tallos, frutos en vaina o flores.",
              "imagen": "img/modFru/hortalizas.jpg",
              "ancho": 200
            },
            {
              "titulo": "Legumbres",
              "texto": "Semillas contenidas en las vainas de las plantas de la familia de las leguminosas. El término legumbres frescas se refiere a los frutos y semillas no maduros de las hortalizas leguminosas.",
              "imagen": "img/modFru/legumbres.jpg",
              "ancho": 200
            },
            {
              "titulo": "Frutas",
              "texto": "El conjunto de frutos comestibles de ciertas plantas cultivadas o silvestres.",
              "imagen": "img/modFru/fruits.jpg",
              "ancho": 200
            },
            {
              "titulo": "Setas",
              "texto": "Son variedades de hongos comestibles, entre los que destacan champiñones, níscalos, boletus, etc.",
              "imagen": "img/modFru/setas.jpg",
              "ancho": 200
            }
          ]
        },
        {
          "clase": "icono",
          "subclase": "sabiasQue",
          "texto": "<b>¿Sabías que...</b><br>en su origen las variedades de zanahorias tenían diferentes colores púrpura, blanco, amarillo… y que según una tradición el actual color naranja se debe a un cruce de variedades realizado deliberadamente en el siglo XVI en Holanda para homenajear a la Casa Real Holandesa de Orange cuyo emblema era el color naranja?",
          "imagen": "img/modFru/carrots.jpg",
          "ancho": 150
        }
      ]
    },
    {
      "titulo": "Origen de las frutas y hortalizas",
      "contenido": [
        {
          "clase": "listaObjetos",
          "contenido": [
            {
              "clase": "imagen",
              "imagen": "img/modFru/frutas.jpg"
            },

            {
              "clase": "listaObjetos",
              "subclase": "columna",
              "contenido": [
                {
                  "clase": "texto",
                  "texto": "Los distintos vegetales que consumimos como alimento tienen su origen en los distintos tipos de tejidos vegetales. En la segunda imagen puedes ver el origen de las hortalizas según la parte de la planta que se consume."
                },
                {
                  "clase": "texto",
                  "texto": "Los frutos (los de sabor dulce reciben el nombre de frutas) se originan a partir de la pared del ovario de la flor (pistilo), la cual por efecto de las hormonas vegetales adopta un grosor y consistencia muy variable, en función del tipo de fruto que se trate."
                }
              ]
            },

            {
              "clase": "imagen",
              "imagen": "img/modFru/verduras.jpg"
            }
          ]
        }
      ]
    },
    {
      "titulo": "Origen de las hortalizas",
      "contenido": [
        {
          "clase": "listaObjetos",
          "contenido": [
            {
              "clase": "texto",
              "texto": "Los distintos vegetales que consumimos como alimento tienen su origen en los distintos tipos de tejidos vegetales. En la imagen verás el origen de las hortalizas según la parte de la planta que se consume."
            },
            {
              "clase": "imagen",
              "imagen": "img/modFru/verduras.jpg"
            }
          ]
        }
      ]
    },
    {
      "titulo": "Origen de las frutas",
      "contenido": [
        {
          "clase": "listaObjetos",
          "contenido": [
            {
              "clase": "texto",
              "texto": "Los frutos (los de sabor dulce reciben el nombre de frutas) se originan a partir de la pared del ovario de la flor (pistilo), la cual por efecto de las hormonas vegetales adopta un grosor y consistencia muy variable, en función del tipo de fruto que se trate."
            },
            {
              "clase": "imagen",
              "imagen": "img/modFru/frutas.jpg"
            }
          ]
        }
      ]
    },
    {
      "titulo": "Clasificación de las hortalizas",
      "contenido": [
        {
          "clase": "icono",
          "subclase": "exclamacion",
          "animacion": "slideInRight",
          "texto": "<center>Sitúa el ratón sobre cada icono para ver la clasificación y algunos ejemplos.</center>"
        },
        {
          "clase": "texto",
          "texto": "<center><b>HORTALIZAS</b><br>Las hortalizas se clasifican según su órgano de consumo en:</center>"
        },
        {
          "clase": "circulo",
          "subclase": "semi",
          "contenido": [
            {
              "imagen": "img/modFru/hraiz.jpg",
              "titulo": "Raíz",
              "texto": "Nabo, rábano, zanahoria, remolacha."
            },
            {
              "imagen": "img/modFru/htuberculos.jpg",
              "titulo": "Tubérculo",
              "texto": "Patata, batata, mandioca o yuca."
            },
            {
              "imagen": "img/modFru/hbulbos.jpg",
              "titulo": "Bulbo",
              "texto": "Ajo, cebolla, puerro."
            },
            {
              "imagen": "img/modFru/htallos.jpg",
              "titulo": "Hojas y tallos tiernos",
              "texto": "Lechuga, perejil, acelga, berro, repollo, espárragos, apio."
            },
            {
              "imagen": "img/modFru/hinflorescencia.jpg",
              "titulo": "Inflorescencia",
              "texto": "Alcachofa, brócoli, coliflor, romanescu."
            },
            {
              "imagen": "img/modFru/hfrutos.jpg",
              "titulo": "Frutos",
              "texto": "Pimiento, berenjena, guindilla, tomate."
            },
            {
              "imagen": "img/modFru/hsemillas.jpg",
              "titulo": "Semilla",
              "texto": "Haba, guisante, alubia, garbanzo, lenteja."
            },
            {
              "imagen": "img/modFru/hpeponides.jpg",
              "titulo": "Pepónides",
              "texto": "Calabaza, pepino, calabacín. También melón y sandía pero que vamos a asignar como Frutas."
            }
          ]
        }
      ]
    },
    {
      "titulo": "Clasificación de las frutas",
      "contenido": [
        {
          "clase": "icono",
          "subclase": "exclamacion",
          "animacion": "slideInRight",
          "texto": "<center>Sitúa el ratón sobre cada icono para ver la clasificación y algunos ejemplos.</center>"
        },
        {
          "clase": "texto",
          "texto": "<center><b>FRUTAS</b></center>"
        },
        {
          "clase": "circulo",
          "subclase": "semi",
          "contenido": [
            {
              "imagen": "img/modFru/fsecos.jpg",
              "titulo": "Frutos secos",
              "texto": "Nuez, avellana, castaña, almendra"
            },
            {
              "imagen": "img/modFru/fhueso.jpg",
              "titulo": "Frutas de hueso",
              "texto": "Melocotón, nectarina, paraguayo, albaricoque, aguacate, ciruela, cereza."
            },
            {
              "imagen": "img/modFru/fpepita.jpg",
              "titulo": "Frutas de pepita",
              "texto": "Manzana, pera, níspero, membrillo."
            },
            {
              "imagen": "img/modFru/fgrano.jpg",
              "titulo": "Frutas de grano",
              "texto": "Fresa e higo."
            },
            {
              "imagen": "img/modFru/fbayas.jpg",
              "titulo": "Bayas",
              "texto": "Frambuesa, grosella, mora, zarzamora."
            },
            {
              "imagen": "img/modFru/fpeponides.jpg",
              "titulo": "Pepónides",
              "texto": "Melón y sandía."
            },
            {
              "imagen": "img/modFru/fcitricos.jpg",
              "titulo": "Cítricos",
              "texto": "Limón, naranja, mandarina, lima, pomelo."
            },
            {
              "imagen": "img/modFru/ftropical.jpg",
              "titulo": "Frutas tropicales",
              "texto": "Kiwi, piña, mango, papaya, plátano, chirimoya, coco."
            }
          ]
        }
      ]
    },
    {
      "titulo": "Composición química: Nutrientes",
      "contenido": [
        {
          "clase": "texto",
          "texto": "Las propiedades nutritivas de frutas y hortalizas dependen de la composición química –nutrientes- del producto: vitaminas, minerales y otros compuestos. Esta composición es propia de cada fruta (y a su vez de su variedad) y de cada hortaliza. <br>Entre sus componentes destacan:<br><br>"
        },
        {
          "clase": "acordeonSub",
          "contenido": [
            {
              "titulo": "Agua",
              "texto": "Es el elemento mayoritario en la composición. Con la excepción de los frutos secos, todas las Frutas y Hortalizas tiene en común un elevado contenido en agua."
            },
            {
              "titulo": "Hidratos de Carbono",
              "texto": "Las hortalizas son ricas en hidratos de carbono complejos (almidón) mientras que las frutas tienen en mayor cantidad hidratos de carbono sencillos o azúcares (fructosa, glucosa y sacarosa). Por esta razón las hortalizas carecen del sabor dulce propio de las frutas (con la excepción del tomate)."
            },
            {
              "titulo": "Fibra",
              "texto": "La fibra tiene composición compleja y confiere a las hortalizas rigidez y sensación de fibrosidad. Es la parte de los alimentos vegetales comestibles que no es digerida por nuestro aparato digestivo."
            },
            {
              "titulo": "Vitaminas",
              "contenido": [
                {
                  "titulo": "En general",
                  "texto": "Son compuestos químicos que el organismo no es capaz de sintetizar (excepto la vitamina D) y son indispensables, en cantidades muy pequeñas, para la vida. Su déficit provoca trastornos y enfermedades, pero también hemos de saber que su exceso puede llegar a provocar problemas muy graves a la salud, aunque cabe reseñar que esto último a través del consumo de alimentos en forma natural es muy difícil. Destacan:"
                },
                {
                  "titulo": "Vitamina A",
                  "texto": "Participa en la regeneración celular (lo que influye en el crecimiento y desarrollo de los huesos), estimula el sistema inmunitario y mejora la visión. También tiene función antioxidante."
                },
                {
                  "titulo": "Vitaminas del grupo B",
                  "texto": "Intervienen en la transformación de los alimentos en energía y son responsables de mantener la salud y el funcionamiento correcto de muchos Sistemas del cuerpo humano (Nervioso, Digestivo, Circulatorio, Inmunológico…)."
                },
                {
                  "titulo": "Vitamina C",
                  "texto": "Imprescindible para la formación de colágeno y en numerosas reacciones del organismo (mantenimiento de cartílagos, huesos y dientes; disminuye los niveles de tensión arterial lo que contribuye a prevenir enfermedades cardiovasculares; ayuda en la asimilación del Hierro; previene o mejora afecciones de la piel, etc…). También tiene función antioxidante."
                },
                {
                  "titulo": "Vitamina E",
                  "texto": "Es un antioxidante natural. Protege al organismo contra los efectos del envejecimiento."
                },
                {
                  "titulo": "Vitamina K",
                  "texto": "Se la conoce como la vitamina de la coagulación, porque sin ella la sangre no coagularía."
                }
              ]
            },
            {
              "titulo": "Minerales",
              "texto": "Los minerales son elementos inorgánicos que el organismo necesita para funcionar, y deben ingerirse con los alimentos. Cumplen variedad de funciones: estructura de huesos y dientes, transporte de oxígeno en glóbulos rojos, transmisión de impulsos nerviosos, contracción muscular, respuesta inmunológica, etc. La composición de frutas y hortalizas aporta un gran número de minerales como hierro, potasio, magnesio, fósforo, etc."
            }
          ]
        },
        {
          "clase": "icono",
          "subclase": "sabiasQue",
          "texto": "<b>¿Sabías qué...</b><br>Las calorías de la fruta dependen casi exclusivamente de su contenido de hidratos de carbono –su contenido en grasas es casi inapreciable-, a excepción del caso del aguacate y del coco, frutas en las que el contenido graso determina su valor energético (en el aguacate la mayor parte es grasa “saludable”, mientras que en el coco la mayor parte es grasa saturada, “menos saludable”)?"
        }
      ]
    },
    {
      "titulo": "Composición química: Colores",
      "contenido": [
        {
          "clase": "texto",
          "texto": "La composición química va a conferir a cada fruta un aroma y un sabor únicos. Pero también va a influir sobre el propio color que presentan frutas y hortalizas.<br><br>El color que presenten puede darnos una idea de su composición química. Tenemos así:"
        },
        {
          "clase": "sliderB",
          "contenido": [
            {
              "titulo": "Color <b>verde</b>",
              "texto": "Es el color de la clorofila por lo que es indicativo de riqueza en Magnesio, mineral que participa en el proceso de relajación muscular (por tanto su carencia puede provocar sensación de cansancio sin causa que lo justifique, tensión muscular y calambres). Contienen, además, sustancias que refuerzan el Sistema Inmunológico (defensas) y son una fuente importante de Vitamina C y fibra.<br>En este grupo destacan: brócoli, lima, kiwi, espinacas, guisantes, lechugas, aguacates y uvas verdes, entre otros.",
              "imagen": "img/modFru/kiwi.jpg",
              "ancho": 600
            },

            {
              "titulo": "Color <b>amarillo/anaranjado</b>",
              "texto": "Es el color de los carotenos cuya acción antioxidante es muy efectiva, aumentando la protección frente al cáncer, fortalecen la vista (ya que son precursores de la Vitamina A), ayudan a combatir infecciones de la piel y tienen propiedades fotoprotectoras al contrarrestar las alteraciones producidas por los rayos UVA (minimizando o reduciendo la flacidez de la piel y la aparición de arrugas). El Beta-caroteno es altamente beneficioso para el Sistema Respiratorio. Frutas y vegetales de color amarillo o naranja destacan por su contenido en Vitamina C y minerales como el potasio.<br>Dentro de este grupo se encuentran: cítricos, melocotón, calabaza, zanahoria, mango y papaya entre otros.",
              "imagen": "img/modFru/mediaNaranja.jpg",
              "ancho": 600
            },
            {
              "titulo": "Color <b>blanco</b>",
              "texto": "Es el color de los polifenoles, que son compuestos antioxidantes que ayudan a reducir el riesgo de enfermedades cardiovasculares y cáncer. Tienen efectos antibacterianos, antimicóticos y antiinflamatorios  y refuerzan el Sistema Inmunológico.<br>En este grupo destacan: ajos, cebollas, pepinos, setas y frutas de carne blanca como plátanos, peras y manzanas.",
              "imagen": "img/modFru/mediaCebolla.jpg",
              "ancho": 600
            },
            {
              "titulo": "Color <b>rojo, morado/azul</b>",
              "texto": "Al igual que frutas y hortalizas de color naranja, poseen carotenos, de los cuales hemos visto sus efectos beneficiosos, pero además, frutas y hortalizas de color rojo intenso/morado son ricas en flavonoides que son compuestos con propiedades antioxidantes que protegen contra la oxidación de vitaminas, enzimas y hormonas. A estos compuestos se les suma otro de color rojo intenso (licopeno) de idéntico efecto. Todos ellos contribuyen a la salud de la memoria y  son compuestos muy beneficiosos para la salud cardiovascular, ya que ayudan a prevenir la hipertensión por sus propiedades vasodilatadoras y reduciendo la formación de placas de colesterol en las arterias.<br>Se incluyen en este grupo: berenjenas, lombardas, ciruelas, uvas tintas, arándanos, moras, tomates, pimientos rojos, rábanos, fresas, frambuesas, cerezas, etc.",
              "imagen": "img/modFru/berries.jpg",
              "ancho": 600
            }
          ]
        },
        {
          "clase": "icono",
          "subclase": "sabiasQue",
          "texto": "<b>¿Sabías qué...</b><br>fresas y kiwis tienen mayor contenido en vitamina C que las naranjas?"
        }
      ]
    },
    {
      "titulo": "Desarrollo de frutas y hortalizas",
      "contenido": [
        {
          "clase": "listaObjetos",
          "contenido": [
            {
              "clase": "listaObjetos",
              "subclase": "columna",
              "contenido": [

                {
                  "clase": "texto",
                  "texto": "La vida de frutas y hortalizas se puede dividir en tres etapas fundamentales:"
                },
                {
                  "clase": "acordeon",
                  "contenido": [
                    {
                      "titulo": "Etapa de desarrollo y crecimiento",
                      "texto": "Durante esta etapa se produce el aumento de volumen hasta alcanzar el tamaño final.",
                      "imagen": "img/modFru/apple.jpg",
                      "ancho": 300
                    },
                    {
                      "titulo": "Maduración",
                      "texto": "Conjunto de procesos de desarrolllo y cambios cuya consecuencia es la adquisición de las características físico-químicas propias.",
                      "imagen": "img/modFru/maduracion.jpg",
                      "ancho": 300
                    },
                    {
                      "titulo": "Senescencia",
                      "texto": "Proceso de envejecimiento de las células de los tejidos, lo que lleva a la muerte del producto.",
                      "imagen": "img/modFru/senescencia.jpg",
                      "ancho": 300
                    }
                  ]
                }
              ]
            },
            {
              "clase": "imagen",
              "imagen": "img/modFru/oranges.jpg"
            }
          ]
        },
        {
          "clase": "texto",
          "texto": "Frutas y hortalizas son estructuras vivas que  después de la recolección, siguen desarrollando procesos metabólicos y mantienen sus sistemas fisiológicos funcionando (respiración, transpiración, etc).<br>Cuando están unidas a la planta, cualquier pérdida de nutrientes o de agua se compensa por el flujo de savia, pero tras la recolección ya no existe ese aporte, así que cuando estas reservas de agua y nutrientes decaen o se agotan, la estructura vegetal colapsa. Por este motivo los vegetales son productos perecederos."
        },
        {
          "clase": "icono",
          "subclase": "sabiasQue",
          "texto": "<b>¿Sabías qué...</b><br>no se debe mantener la fruta en bolsas o envases de plástico, ya que éstos retienen la humedad y el calor que libera la fruta, lo que provoca su enmohecimiento, deterioro y pudrición?"
        }
      ]
    },
    {
      "titulo": "Maduración",
      "contenido": [
        {
          "clase": "texto",
          "texto": "La maduración de las frutas está ligada a una serie de complejas transformaciones de su composición química.<br>Cuando se recolectan las frutas, sus tejidos siguen activos y <b>respiran</b>. Estos procesos tienen gran importancia porque influyen en los cambios que se producen durante el almacenamiento, transporte y comercialización de las frutas."
        },
        {
          "clase": "listaObjetos",
          "contenido": [
            {
              "clase": "imagen",
              "imagen": "img/modFru/frutaverde.jpg",
              "ancho": 250
            },
            {
              "clase": "lista",
              "titulo": "Durante la maduración, se producen unos cambios esenciales:",
              "contenido": [
                {
                  "punto": "Cambios en la respiración."
                },
                {
                  "punto": "Cambios en la composición química."
                }
              ]
            },
            {

              "clase": "imagen",
              "imagen": "img/modFru/frutanaranja.jpg",
              "ancho": 250
            }
          ]
        },
        {
          "clase": "imagen",
          "imagen": "img/modFru/manzanaCorte.png",
          "ancho": 400
        },

        {
          "clase": "icono",
          "subclase": "sabiasQue",
          "texto": "<b>¿Sabías qué...</b><br>podemos acelerar la maduración de las frutas si las envolvemos en papel de periódico ya que así se retiene el etileno que va liberando y lo mismo sucede con las frutas verdes si las guardamos junto a frutas –climatéricas- maduras, ya que éstas liberan mucho etileno?"
        }



      ]
    },
    {
      "titulo": "Maduración: Cambios en la respiración",
      "contenido": [
        {
          "clase": "texto",
          "texto": "<b>Respiración:</b><br><br>Mientras la fruta se está desarrollando la respiración va aumentando, hasta llegar a un punto en el que empieza a disminuir lentamente. A partir de este punto si la intensidad respiratoria:<br><br>"
        },
        {
          "clase": "acordeon",
          "contenido": [
            {
              "titulo": "Aumenta",
              "texto": "Aumenta, de repente, hasta alcanzar un valor máximo (punto climatérico) hablamos de frutas climatéricas. En ese punto la fruta llega a su estado de maduración y a partir del mismo la intensidad respiratoria vuelve a descender hasta la muerte de todas las células de la fruta. Son frutas que pueden seguir madurando aunque se hayan recolectado. Así, se recolectan  antes de que estén maduras porque aguantan mucho mejor el transporte y el almacenamiento. Son ejemplo de este tipo de frutas: plátano, pera, manzana.",
              "imagen": "img/modFru/graficoMaduracion.png",
              "ancho": 500
            },
            {
              "titulo": "Sigue disminuyendo",
              "texto": "Sigue disminuyendo hasta que todas las células se mueren. Son frutas no climatéricas y no sufren transformaciones importantes una vez se han recolectado, por lo que deben dejarse madurar en la planta.  Por eso estas frutas no se venden si no está maduras, ya que no son capaces de madurar una vez recolectadas. Por ejemplo: fresas, uvas, cítricos.",
              "imagen": "img/modFru/graficoNoclimaterico.png",
              "ancho": 500
            }
          ]
        },
        {
          "clase": "icono",
          "subclase": "sabiasQue",
          "texto": "<b>¿Sabías qué...</b><br>la temperatura influye directamente sobre la respiración de la fruta, de tal forma que a mayor temperatura mayor es la velocidad de respiración? Por eso si se mantiene baja la temperatura, se disminuye la respiración del producto y se ayuda a prolongar su vida útil?"
        }
      ]
    },
    {
      "titulo": "Maduración: Cambios en la composición química",
      "fondo": "img/modFru/strawberryPlant.jpg",
      "contenido": [
        {
          "clase": "texto",
          "subclase": "recuadro",
          "opacidad": 0.7,
          "texto": "Cambios en la composición química:<br>La mayoría de los componentes de la fruta se transforman, lo que conlleva cambios en el color, olor, sabor y textura de la fruta.<br>El fruto verde, está compuesto principalmente por agua, clorofila, almidón, celulosas y ácidos. Esto hace que tenga color verde, una textura dura y el sabor sea insípido o ácido."
        },
        {
          "clase": "lista",
          "subclase": "recuadro",
          "opacidad": 0.7,
          "titulo": "Con la maduración:",
          "contenido": [
            {
              "punto": "El almidón se transforma en azúcares sencillos, lo que hace que el sabor sea más dulce."
            },
            {
              "punto": "Las pectinas se solubilizan, lo que provoca un ablandamiento de la fruta."
            },
            {
              "punto": "La concentración de ácidos disminuye (excepto en los cítricos) por lo que su sabor es menos ácido."
            },
            {
              "punto": "Se crean pigmentos que hacen que la fruta pase de tener color verde a tener su color característico y se crean otros compuestos aromáticos que aportan sabores y olores característicos a cada fruta."
            },
            {
              "punto": "Se aumenta la concentración de etileno (hormona vegetal), compuesto gaseoso que inicia y acelera la maduración."
            }
          ]
        }
      ]
    },
    {
      "titulo": "Envejecimiento de las frutas",
      "contenido": [
        {
          "clase": "listaObjetos",
          "contenido": [
            {
              "clase": "lista",
              "titulo": "Durante el envejecimiento se siguen produciendo cambios en la composición química:",
              "contenido": [
                {
                  "punto": "Los azúcares se transforman en alcoholes y dióxido de carbono."
                },
                {
                  "punto": "Los tejidos se degradan y la estructura de la fruta se altera, permitiendo el paso de microorganismos que alteran la composición y producen compuestos que dan malos olores y sabores."
                }
              ]
            },
            {
              "clase": "imagen",
              "imagen": "img/modFru/manzanas3.jpg"
            }
          ]
        },
        {
          "clase": "listaObjetos",
          "contenido": [
            {
              "clase": "imagen",
              "imagen": "img/modFru/banana1.png"
            },
            {
              "clase": "imagen",
              "imagen": "img/modFru/banana2.png"
            },
            {
              "clase": "imagen",
              "imagen": "img/modFru/banana3.jpg"
            }
          ]
        },
        {
          "clase": "icono",
          "subclase": "sabiasQue",
          "texto": "<b>¿Sabías qué...</b><br>los tomates fueron considerados tóxicos cuando llegaron por primera vez a Europa? Algo parecido sucedió con los pepinos, en los que hubo un momento que se consideraron  venenosos por lo que se les rascaba la piel para “eliminar” el veneno."
        }
      ]
    },
    {
      "titulo": "Deterioro",
      "fondo": "img/modFru/fruitsFondo.jpg",
      "contenido": [
        {
          "clase": "texto",
          "subclase": "recuadro",
          "texto": "No existe gran diferencia entre frutas y hortalizas a la hora de sufrir alteraciones.<br><center>El deterioro puede producirse por:</center>"
        },
        {
          "clase": "tabs",
          "animacion": "fadeInRight",
          "contenido": [
            {
              "titulo": "Heridas, golpes",
              "texto": "Heridas, golpes y zonas machacadas provocadas durante su  recolección, transporte y almacenamiento. Estas zonas son más sensibles al ataque de microorganismos, que originarán olores y sabores desagradables.",
              "imagen": "img/modFru/golpes.jpg",
              "ancho": 200
            },
            {
              "titulo": "Insectos",
              "texto": "Lesiones y daños causadas por insectos y orugas. Provocan graves modificaciones (principalmente del aspecto y características organolépticas) que las hacen inaceptables comercialmente. Estas lesiones favorecen, además, el ataque de microorganismos.",
              "imagen": "img/modFru/caracol.jpg",
              "ancho": 200
            },
            {
              "titulo": "Microorganismos",
              "texto": "Además de las zonas dañadas, muchas frutas y hortalizas pueden ser atacadas por microorganismos, lo que les conferirán olores y sabores desagradables. La composición química de frutas y hortalizas las hace menos sensibles al ataque de bacterias (provocan manchas, podredumbres…) pero por el contrario favorece el ataque por hongos (levaduras y mohos), siendo éstos los principales causantes de podredumbres o enmohecimientos.",
              "imagen": "img/modFru/chungas.jpg",
              "ancho": 200
            },
            {
              "titulo": "Envejecimiento",
              "texto": "Se adquiere una textura blanda y se hacen muy sensibles a alteraciones microbiológicas (podredumbres) y alteraciones internas.",
              "imagen": "img/modFru/stillif.jpg",
              "ancho": 200
            },
            {
              "titulo": "Almacenamiento incorrecto",
              "texto": "1. Si la temperatura es demasiado baja pueden producirse coloraciones extrañas en la pulpa y en la piel, dando apariencia de quemaduras. Suele ser frecuente en productos tropicales transportados o almacenados a temperaturas más bajas de las recomendadas.<br>2. Si la humedad es demasiado baja, para compensarla, se produce en la fruta u hortaliza una deshidratación, lo que provoca el marchitamiento y el arrugado. Por el contrario, una humedad excesiva favorece el desarrollo de mohos.<br>3. Algunos productos deben protegerse de la luz para evitar la germinación o, como las patatas, que se vuelvan verdes (lo que indica la presencia de solanina, que es una sustancia tóxica).<br>4. Almacenar juntos productos que liberan mucho etileno junto a productos muy sensibles a éste, puede provocar una maduración prematura no deseada.",
              "imagen": "img/modFru/appetiz.jpg",
              "ancho": 200
            }
          ]
        },
        {
          "clase": "icono",
          "subclase": "sabiasQue",
          "texto": "<b>¿Sabías que...</b><br>almacenar las patatas a bajas temperaturas provoca que el almidón se transforme en azúcares simples y por eso las patatas adquieren un sabor dulce? (Pero también has de saber que hay variedades más dulces que otras)."
        }
      ]
    },
    {
      "titulo": "Beneficios que aportan",
      "contenido": [
        {
          "clase": "texto",
          "texto": "Frutas y Hortalizas juegan un papel trascendental en el equilibrio de la dieta humana por sus cualidades nutritivas:"
        },
        {
          "clase": "listaObjetos",
          "contenido": [
            {
              "clase": "imagen",
              "imagen": "img/modFru/salad.jpg",
              "ancho": 200
            },
            {
              "clase": "texto",
              "texto": "Aportan agua que nos mantiene en un grado adecuado de hidratación y favorece la eliminación de sustancias tóxicas de nuestro organismo."
            }
          ]
        },
        {
          "clase": "listaObjetos",
          "contenido": [
            {
              "clase": "imagen",
              "imagen": "img/modFru/paprika.jpg",
              "ancho": 200
            },
            {
              "clase": "texto",
              "texto": "Aportan muchas vitaminas, sobre todo vitamina C de las que son fuente casi exclusiva."
            }
          ]
        },
        {
          "clase": "listaObjetos",
          "contenido": [
            {
              "clase": "imagen",
              "imagen": "img/modFru/moras.jpg",
              "ancho": 200
            },
            {
              "clase": "texto",
              "texto": "Aportan compuestos y sustancias antioxidantes."
            }
          ]
        },
        {
          "clase": "listaObjetos",
          "contenido": [
            {
              "clase": "imagen",
              "imagen": "img/modFru/artichokes.jpg",
              "ancho": 200
            },
            {
              "clase": "texto",
              "texto": "Contienen fibra que ayuda a regular la función del intestino."
            }
          ]
        },
        {
          "clase": "lista",
          "titulo": "Y, por todo ello, está probado que una adecuada alimentación – especialmente la ingesta de verduras, hortalizas y frutas- puede ayudar a:",
          "contenido": [
            {
              "punto": "Prevenir enfermedades cardiovasculares, obesidad, e incluso algunos tipos de cáncer como el de boca, faringe, laringe, pulmón, esófago, estómago, colon, mama y vejiga."
            },
            {
              "punto": "Disminuir el deterioro causado por el proceso de envejecimiento."
            }
          ]
        },
        {
          "clase": "icono",
          "subclase": "sabiasQue",
          "texto": "<b>¿Sabías qué...</b><br>el pimiento contiene más vitamina C que la naranja?<br><b>o que...</b> fresas y kiwis también tienen mayor contenido en vitamina C que las naranjas?"
        }
      ]
    },
    {
      "titulo": "Beneficios",
      "contenido": [
        {
          "clase": "texto",
          "animacion": "flash",
          "texto": "Por el contrario, los beneficios de una buena práctica higiénica:"
        },
        {
          "clase": "diagrama",
          "cajas": [
            {
              "id": 1,
              "forma": "rect",
              "texto": "Buena reputación de la empresa",
              "ancho": 1300,
              "alto": 40,
              "x": 1,
              "y": 1,
              "relleno": "#B3E5FC",
              "borde": "#1E88E5",
              "anchoBorde": 3,
              "orden": 1
            },
            {
              "id": 2,
              "forma": "rect",
              "texto": "<span class='h5'>Clientes satisfechos</span>",
              "ancho": 250,
              "alto": 40,
              "x": 1,
              "y": 75,
              "relleno": "#E1F5FE",
              "borde": "#1E88E5",
              "anchoBorde": 1,
              "orden": 3
            },
            {
              "id": 3,
              "forma": "rect",
              "texto": "<span class='h5'>Publicidad positiva</span>",
              "ancho": 250,
              "alto": 40,
              "x": 1,
              "y": 150,
              "relleno": "#E1F5FE",
              "borde": "#1E88E5",
              "anchoBorde": 1,
              "orden": 5
            },
            {
              "id": 4,
              "forma": "rect",
              "texto": "<span class='h5'>Aumento de clientes<br>Facilidad para captar clientes<br>Mayor demanda de artículos</span>",
              "ancho": 250,
              "alto": 100,
              "x": 1,
              "y": 250,
              "relleno": "#E1F5FE",
              "borde": "#1E88E5",
              "anchoBorde": 1,
              "orden": 7
            },
            {
              "id": 5,
              "forma": "rect",
              "texto": "<span class='h5'>Aumento de las ventas</span>",
              "ancho": 200,
              "alto": 40,
              "x": 300,
              "y": 310,
              "relleno": "#E1F5FE",
              "borde": "#1E88E5",
              "anchoBorde": 1,
              "orden": 9
            },
            {
              "id": 6,
              "forma": "rect",
              "texto": "Aumento de beneficios",
              "ancho": 1300,
              "alto": 40,
              "x": 1,
              "y": 480,
              "relleno": "#C8E6C9",
              "borde": "#4CAF50",
              "anchoBorde": 3,
              "orden": 25
            },
            {
              "id": 7,
              "forma": "rect",
              "texto": "<span class='h5 estrecho'>Mayores salarios y primas</span>",
              "ancho": 160,
              "alto": 70,
              "x": 317,
              "y": 190,
              "borde": "#B39DDB",
              "anchoBorde": 1,
              "orden": 21
            },
            {
              "id": 8,
              "forma": "rect",
              "texto": "<span class='h5 estrecho'>Mayor motivación en el trabajo<br>Mejor rendimiento de la plantilla<br>Menor movilidad de plantilla<br>Ambiente de trabajo más seguro y agradable</span>",
              "ancho": 330,
              "alto": 200,
              "x": 550,
              "y": 160,
              "relleno": "#B2EBF2",
              "borde": "#1E88E5",
              "anchoBorde": 1,
              "orden": 13
            },
            {
              "id": 9,
              "forma": "rect",
              "texto": "<span class='h5 estrecho'>Mayor autoestima del personal</span>",
              "ancho": 330,
              "alto": 40,
              "x": 550,
              "y": 75,
              "relleno": "#B2EBF2",
              "borde": "#1E88E5",
              "anchoBorde": 1,
              "orden": 11
            },
            {
              "id": 10,
              "forma": "rect",
              "texto": "<span class='h5 estrecho'>Adecuación a la Ley</span>",
              "ancho": 350,
              "alto": 40,
              "x": 950,
              "y": 100,
              "borde": "#B2EBF2",
              "anchoBorde": 3,
              "dashArray": "5,5",
              "orden": 15
            },
            {
              "id": 11,
              "forma": "rect",
              "texto": "<span class='h5 estrecho'>Satisfacción de las Autoridades Sanitarias</span>",
              "ancho": 350,
              "alto": 70,
              "x": 950,
              "y": 190,
              "borde": "#B2EBF2",
              "anchoBorde": 3,
              "dashArray": "5,5",
              "orden": 17
            },
            {
              "id": 12,
              "forma": "rect",
              "texto": "<span class='h5 estrecho'>Menor estrés al cumplir con los requisitos de Sanidad.<br>(La vigilancia demasiado estrecha del Inspector de Sanidad puede llegar a ser estresante)</span>",
              "ancho": 350,
              "alto": 150,
              "x": 950,
              "y": 300,
              "borde": "#B2EBF2",
              "anchoBorde": 3,
              "dashArray": "5,5",
              "orden": 19
            },
            {
              "id": 13,
              "forma": "rect",
              "texto": "Ganancia económica",
              "ancho": 1300,
              "alto": 40,
              "x": 1,
              "y": 570,
              "relleno": "#C8E6C9",
              "borde": "#4CAF50",
              "anchoBorde": 3,
              "orden": 27

            },
            {
              "id": 14,
              "forma": "rect",
              "texto": "<span class='h4'>Posible ampliación del negocio</span>",
              "ancho": 300,
              "alto": 50,
              "x": 500,
              "y": 660,
              "borde": "#4CAF50",
              "anchoBorde": 3,
              "orden": 29
            },
            {
              "id": 15,
              "forma": "rect",
              "texto": "<span class='h4'>Nuevos puestos de trabajo<br>Ascensos</span>",
              "ancho": 300,
              "alto": 100,
              "x": 500,
              "y": 745,
              "borde": "#4CAF50",
              "anchoBorde": 3,
              "orden": 31
            }
          ],
          "enlaces": [
            {
              "origen": 1,
              "destino": 2,
              "color": "#1E88E5",
              "orden": 2
            },
            {
              "origen": 1,
              "destino": 9,
              "color": "#1E88E5",
              "orden": 10
            },
            {
              "origen": 2,
              "destino": 3,
              "color": "#1E88E5",
              "orden": 4
            },
            {
              "origen": 3,
              "destino": 4,
              "color": "#1E88E5",
              "orden": 6
            },
            {
              "origen": 4,
              "destino": 5,
              "color": "#1E88E5",
              "orden": 8
            },
            {
              "origen": 5,
              "destino": 7,
              "color": "#1E88E5",
              "orden": 20
            },
            {
              "origen": 5,
              "destino": 6,
              "color": "#1E88E5",
              "orden": 24
            },

            {
              "origen": 7,
              "destino": 8,
              "color": "#1E88E5",
              "orden": 22
            },
            {
              "origen": 9,
              "destino": 8,
              "color": "#1E88E5",
              "orden": 12
            },
            {
              "origen": 8,
              "destino": 10,
              "color": "#1E88E5",
              "orden": 14
            },
            {
              "origen": 8,
              "destino": 5,
              "color": "#1E88E5",
              "orden": 23
            },
            {
              "origen": 10,
              "destino": 11,
              "color": "#1E88E5",
              "orden": 16
            },
            {
              "origen": 11,
              "destino": 12,
              "color": "#1E88E5",
              "orden": 18
            },
            {
              "origen": 6,
              "destino": 13,
              "color": "#4CAF50",
              "orden": 26
            },
            {
              "origen": 13,
              "destino": 14,
              "color": "#4CAF50",
              "orden": 28
            },
            {
              "origen": 14,
              "destino": 15,
              "color": "#4CAF50",
              "orden": 30
            }
          ]
        }
      ]
    },
    {
      "titulo": "Diagrama de flujo",
      "contenido": [
        {
          "clase": "texto",
          "animacion": "fadeInRight",
          "texto": "A grandes rasgos podríamos definir un diagrama de flujo de frutas y verduras desde su origen hasta el consumidor final según las siguientes etapas:"
        },
        {
          "clase": "diagrama",
          "retardo": 500,
          "cajas": [
            {
              "id": 1,
              "forma": "rect",
              "texto": "Producción Primaria",
              "ancho": 300,
              "alto": 60,
              "x": 400,
              "y": 1,
              "relleno": "#ffffff",
              "borde": "#65acb0",
              "anchoBorde": 3,
              "orden": 1
            },
            {
              "id": 2,
              "forma": "rect",
              "texto": "Recolección",
              "ancho": 300,
              "alto": 60,
              "x": 400,
              "y": 100,
              "relleno": "#ffffff",
              "borde": "#65acb0",
              "anchoBorde": 3,
              "orden": 3
            },
            {
              "id": 3,
              "forma": "rect",
              "texto": "Transporte",
              "ancho": 300,
              "alto": 60,
              "x": 400,
              "y": 200,
              "relleno": "#ffffff",
              "borde": "#65acb0",
              "anchoBorde": 3,
              "orden": 5
            },
            {
              "id": 4,
              "forma": "rect",
              "texto": "Almacenamiento",
              "ancho": 300,
              "alto": 60,
              "x": 400,
              "y": 300,
              "relleno": "#ffffff",
              "borde": "#65acb0",
              "anchoBorde": 3,
              "orden": 7
            },
            {
              "id": 4.5,
              "forma": "rect",
              "texto": "<span class='h5 estrecho'>PRODUCTOS FRESCOS</span>",
              "ancho": 350,
              "alto": 40,
              "x": 950,
              "y": 100,
              "borde": "#B2EBF2",
              "anchoBorde": 3,
              "dashArray": "5,5",
              "orden": 7.5
            },
            {
              "id": 5,
              "forma": "rect",
              "texto": "Frutería",
              "ancho": 300,
              "alto": 60,
              "x": 1,
              "y": 400,
              "relleno": "#ffffff",
              "borde": "#65acb0",
              "anchoBorde": 3,
              "orden": 9
            },
            {
              "id": 6,
              "forma": "rect",
              "texto": "Envasado y Transporte",
              "ancho": 300,
              "alto": 60,
              "x": 1,
              "y": 500,
              "relleno": "#ffffff",
              "borde": "#65acb0",
              "anchoBorde": 3,
              "orden": 11
            },
            {
              "id": 8,
              "forma": "rect",
              "texto": "Exposición y venta",
              "ancho": 300,
              "alto": 60,
              "x": 1,
              "y": 700,
              "relleno": "#ffffff",
              "borde": "#65acb0",
              "anchoBorde": 3,
              "orden": 13
            },
            {
              "id": 9,
              "forma": "rect",
              "texto": "Industria procesadora",
              "ancho": 300,
              "alto": 60,
              "x": 800,
              "y": 400,
              "relleno": "#ffffff",
              "borde": "#65acb0",
              "anchoBorde": 3,
              "orden": 15
            },
            {
              "id": 10,
              "forma": "rect",
              "texto": "Almacenamiento",
              "ancho": 300,
              "alto": 60,
              "x": 800,
              "y": 500,
              "relleno": "#ffffff",
              "borde": "#65acb0",
              "anchoBorde": 3,
              "orden": 17
            },
            {
              "id": 11,
              "forma": "rect",
              "texto": "Acondicionamiento",
              "ancho": 300,
              "alto": 60,
              "x": 800,
              "y": 600,
              "relleno": "#ffffff",
              "borde": "#65acb0",
              "anchoBorde": 3,
              "orden": 19
            },
            {
              "id": 12,
              "forma": "rect",
              "texto": "Procesado",
              "ancho": 300,
              "alto": 60,
              "x": 800,
              "y": 700,
              "relleno": "#ffffff",
              "borde": "#65acb0",
              "anchoBorde": 3,
              "orden": 21
            },
            {
              "id": 13,
              "forma": "rect",
              "texto": "Envasado",
              "ancho": 300,
              "alto": 60,
              "x": 800,
              "y": 800,
              "relleno": "#ffffff",
              "borde": "#65acb0",
              "anchoBorde": 3,
              "orden": 23
            },
            {
              "id": 14,
              "forma": "rect",
              "texto": "Almacenamiento / Distribución",
              "ancho": 300,
              "alto": 60,
              "x": 800,
              "y": 900,
              "relleno": "#ffffff",
              "borde": "#65acb0",
              "anchoBorde": 3,
              "orden": 25
            }
          ],
          "enlaces": [
            {
              "origen": 1,
              "destino": 2,
              "color": "#65acb0",
              "orden": 2
            },
            {
              "origen": 2,
              "destino": 3,
              "color": "#65acb0",
              "orden": 4
            },
            {
              "origen": 3,
              "destino": 4,
              "color": "#65acb0",
              "orden": 6
            },
            {
              "origen": 4,
              "destino": 5,
              "color": "#65acb0",
              "orden": 8
            },
            {
              "origen": 5,
              "destino": 6,
              "color": "#65acb0",
              "orden": 10
            },
            {
              "origen": 6,
              "destino": 7,
              "color": "#65acb0",
              "orden": 12
            },
            {
              "origen": 4,
              "destino": 8,
              "color": "#65acb0",
              "orden": 14
            },
            {
              "origen": 8,
              "destino": 9,
              "color": "#65acb0",
              "orden": 16
            },
            {
              "origen": 9,
              "destino": 10,
              "color": "#65acb0",
              "orden": 18
            },
            {
              "origen": 10,
              "destino": 11,
              "color": "#65acb0",
              "orden": 20
            },
            {
              "origen": 11,
              "destino": 12,
              "color": "#65acb0",
              "orden": 22
            },
            {
              "origen": 12,
              "destino": 13,
              "color": "#65acb0",
              "orden": 24
            }
          ]
        }
      ]
    },
    {
      "titulo": "Alteraciones",
      "contenido": [
        {
          "clase": "listaObjetos",
          "contenido": [
            {
              "clase": "lista",
              "titulo": "No existe gran diferencia entre frutas y hortalizas a la hora de sufrir alteraciones.<br>El deterioro puede producirse por:",
              "contenido": [
                {
                  "punto": "Heridas, golpes y zonas machacadas provocadas durante su  recolección, transporte y almacenamiento. Estas zonas son más sensibles al ataque de microorganismos, que originarán olores y sabores desagradables."
                },
                {
                  "punto": "Lesiones y daños causadas por insectos y orugas. Provocan graves modificaciones (principalmente del aspecto y características organolépticas) que las hacen inaceptables comercialmente. Estas lesiones favorecen, además, el ataque de microorganismos."
                },
                {
                  "punto": "Alteración por microorganismos. Además de las zonas dañadas, muchas frutas y hortalizas pueden ser atacadas por microorganismos, lo que les conferirán olores y sabores desagradables. La composición química de frutas y hortalizas las hace menos sensibles al ataque de bacterias (provocan manchas, podredumbres…) pero por el contrario favorece el ataque por hongos (levaduras y mohos), siendo éstos los principales causantes de podredumbres o enmohecimientos."
                },
                {
                  "punto": "Envejecimiento. Se adquiere una textura blanda y se hacen muy sensibles a alteraciones microbiológicas (podredumbres) y alteraciones internas."
                }
              ]
            },
            {
              "clase": "listaObjetos",
              "subclase": "columna",
              "contenido": [
                {
                  "clase": "imagen",
                  "imagen": "img/modFru/caracol.jpg"
                },
                {
                  "clase": "imagen",
                  "imagen": "img/modFru/manzanaFea.jpg"
                }
              ]
            }
          ]
        },
        {
          "clase": "lista",
          "titulo": "Condiciones no apropiadas de almacenamiento: (temperatura, humedad, luz, etc)",
          "contenido": [
            {
              "punto": "Si la temperatura es demasiado baja pueden producirse coloraciones extrañas en la pulpa y en la piel, dando apariencia de quemaduras. Suele ser frecuente en productos tropicales transportados o almacenados a temperaturas más bajas de las recomendadas."
            },
            {
              "punto": "Si la humedad es demasiado baja, para compensarla, se produce en la fruta u hortaliza una deshidratación, lo que provoca el marchitamiento y el arrugado. Por el contrario, una humedad excesiva favorece el desarrollo de mohos."
            },
            {
              "punto": "Algunos productos deben protegerse de la luz para evitar la germinación o, como las patatas, que se vuelvan verdes (lo que indica la presencia de solanina, que es una sustancia tóxica)."
            },
            {
              "punto": "Almacenar juntos productos que liberan mucho etileno junto a productos muy sensibles a éste, puede provocar una maduración prematura no deseada."
            }
          ]
        },
        {
          "clase": "listaObjetos",
          "contenido": [
            {
              "clase": "imagen",
              "imagen": "img/modFru/patatanegra.png"
            },
            {
              "clase": "icono",
              "subclase": "sabiasQue",
              "texto": "<b>Sabías que…</b><br> almacenar las patatas a bajas temperaturas provoca que el almidón se transforme en azúcares simples y por eso las patatas adquieren un sabor dulce? (Pero también has de saber que hay variedades más dulces que otras)."
            }
          ]
        }
      ]
    },
    {
      "titulo": "Diagrama de flujo",
      "contenido": [
        {
          "clase": "texto",
          "animacion": "fadeInRight",
          "texto": "A grandes rasgos podríamos definir un diagrama de flujo de frutas y verduras desde su origen hasta el consumidor final según las siguientes etapas:"
        },
        {
          "clase": "diagrama",
          "retardo": 1,
          "cajas": [
            {
              "id": 1,
              "forma": "rect",
              "texto": "Producción Primaria",
              "ancho": 300,
              "alto": 60,
              "x": 400,
              "y": 1,
              "relleno": "#ffffff",
              "borde": "#65acb0",
              "anchoBorde": 3,
              "orden": 1
            },
            {
              "id": 2,
              "forma": "rect",
              "texto": "Recolección",
              "ancho": 300,
              "alto": 60,
              "x": 400,
              "y": 100,
              "relleno": "#ffffff",
              "borde": "#65acb0",
              "anchoBorde": 3,
              "orden": 3
            },
            {
              "id": 3,
              "forma": "rect",
              "texto": "Transporte",
              "ancho": 300,
              "alto": 60,
              "x": 400,
              "y": 200,
              "relleno": "#ffffff",
              "borde": "#65acb0",
              "anchoBorde": 3,
              "orden": 5
            },
            {
              "id": 4,
              "forma": "rect",
              "texto": "Almacenamiento",
              "ancho": 300,
              "alto": 60,
              "x": 400,
              "y": 300,
              "relleno": "#ffffff",
              "borde": "#65acb0",
              "anchoBorde": 3,
              "orden": 7
            },
            {
              "id": 5,
              "forma": "rect",
              "texto": "Frutería",
              "ancho": 300,
              "alto": 60,
              "x": 1,
              "y": 400,
              "relleno": "#ffffff",
              "borde": "#65acb0",
              "anchoBorde": 3,
              "orden": 9
            },
            {
              "id": 6,
              "forma": "rect",
              "texto": "Envasado y Transporte",
              "ancho": 300,
              "alto": 60,
              "x": 1,
              "y": 500,
              "relleno": "#ffffff",
              "borde": "#65acb0",
              "anchoBorde": 3,
              "orden": 11
            },
            {
              "id": 8,
              "forma": "rect",
              "texto": "Exposición y venta",
              "ancho": 300,
              "alto": 60,
              "x": 1,
              "y": 700,
              "relleno": "#ffffff",
              "borde": "#65acb0",
              "anchoBorde": 3,
              "orden": 13
            },
            {
              "id": 9,
              "forma": "rect",
              "texto": "Industria procesadora",
              "ancho": 300,
              "alto": 60,
              "x": 800,
              "y": 400,
              "relleno": "#ffffff",
              "borde": "#65acb0",
              "anchoBorde": 3,
              "orden": 15
            },
            {
              "id": 10,
              "forma": "rect",
              "texto": "Almacenamiento",
              "ancho": 300,
              "alto": 60,
              "x": 800,
              "y": 500,
              "relleno": "#ffffff",
              "borde": "#65acb0",
              "anchoBorde": 3,
              "orden": 17
            },
            {
              "id": 11,
              "forma": "rect",
              "texto": "Acondicionamiento",
              "ancho": 300,
              "alto": 60,
              "x": 800,
              "y": 600,
              "relleno": "#ffffff",
              "borde": "#65acb0",
              "anchoBorde": 3,
              "orden": 19
            },
            {
              "id": 12,
              "forma": "rect",
              "texto": "Procesado",
              "ancho": 300,
              "alto": 60,
              "x": 800,
              "y": 700,
              "relleno": "#ffffff",
              "borde": "#65acb0",
              "anchoBorde": 3,
              "orden": 21
            },
            {
              "id": 13,
              "forma": "rect",
              "texto": "Envasado",
              "ancho": 300,
              "alto": 60,
              "x": 800,
              "y": 800,
              "relleno": "#ffffff",
              "borde": "#65acb0",
              "anchoBorde": 3,
              "orden": 23
            },
            {
              "id": 14,
              "forma": "rect",
              "texto": "Almacenamiento / Distribución",
              "ancho": 300,
              "alto": 60,
              "x": 800,
              "y": 900,
              "relleno": "#ffffff",
              "borde": "#65acb0",
              "anchoBorde": 3,
              "orden": 25
            }
          ],
          "enlaces": [
            {
              "origen": 1,
              "destino": 2,
              "color": "#65acb0",
              "orden": 2
            },
            {
              "origen": 2,
              "destino": 3,
              "color": "#65acb0",
              "orden": 4
            },
            {
              "origen": 3,
              "destino": 4,
              "color": "#65acb0",
              "orden": 6
            },
            {
              "origen": 4,
              "destino": 5,
              "color": "#65acb0",
              "orden": 8
            },
            {
              "origen": 5,
              "destino": 6,
              "color": "#65acb0",
              "orden": 10
            },
            {
              "origen": 6,
              "destino": 7,
              "color": "#65acb0",
              "orden": 12
            },
            {
              "origen": 4,
              "destino": 8,
              "color": "#65acb0",
              "orden": 14
            },
            {
              "origen": 8,
              "destino": 9,
              "color": "#65acb0",
              "orden": 16
            },
            {
              "origen": 9,
              "destino": 10,
              "color": "#65acb0",
              "orden": 18
            },
            {
              "origen": 10,
              "destino": 11,
              "color": "#65acb0",
              "orden": 20
            },
            {
              "origen": 11,
              "destino": 12,
              "color": "#65acb0",
              "orden": 22
            },
            {
              "origen": 12,
              "destino": 13,
              "color": "#65acb0",
              "orden": 24
            }
          ]
        }
      ]
    },
    {
      "titulo": "Diagrama de flujo IMG",
      "contenido": [
        {
          "clase": "texto",
          "animacion": "fadeInRight",
          "texto": "A grandes rasgos podríamos definir un diagrama de flujo de frutas y verduras desde su origen hasta el consumidor final según las siguientes etapas:"
        },
        {
          "clase": "imagen",
          "imagen": "img/modFru/diagrama.png"
        }
      ]
    },
    {
      "titulo": "Contaminantes en frutas y hortalizas",
      "contenido": [
        {
          "clase": "texto",
          "texto": "Frutas y hortalizas pueden contaminarse en cualquier punto desde la producción primaria hasta el consumidor final. Aunque cada una de dichas etapas tendrá unos peligros asociados específicos, vamos a diferenciar tres grandes bloques:"
        },
        {
          "clase": "listaObjetos",
          "contenido": [
            {
              "clase": "texto",
              "subclase": "celo",
              "texto": "<b>Contaminación de origen:</b><br>En este bloque se incluyen aquellos peligros debidos al hábitat o entorno en el que se realice la Producción Primaria o contaminación durante su recolección."
            },
            {
              "clase": "texto",
              "subclase": "celo",
              "texto": "<b>Conteminación de productos frescos:</b><br>En este bloque se incluyen aquellos peligros asociados a los productos destinados a ser vendidos en fresco o a productos de cuarta gama."
            },
            {
              "clase": "texto",
              "subclase": "celo",
              "texto": "<b>Contaminación de productos elaborados:</b><br>En este bloque se incluyen aquellos peligros asociados a los productos destinados a ser procesados."
            }
          ]
        },
        {
          "clase": "icono",
          "subclase": "definicion",
          "texto": "<b>Definición:</b><br>Productos de Cuarta Gama.<br>Se entiende por cuarta gama al procesado mínimo de hortalizas y frutas frescas limpias, troceadas y envasadas para su consumo.<br>El producto mantiene sus propiedades naturales y frescas, pero con la diferencia que ya viene lavado, troceado y envasado en bandejas o bolsas en atmósferas especiales y que <b>necesitan refrigeración</b> para una correcta conservación."
        }
      ]
    },
    {
      "titulo": "Recolección",
      "contenido": [
        {
          "clase": "listaObjetos",
          "contenido": [
            {
              "clase": "lista",
              "titulo": "En esta etapa puede producirse contaminación de los alimentos debido a  unas malas prácticas higiénicas en la manipulación de frutas y verduras. Para evitar esto:",
              "contenido": [
                {
                  "punto": "El personal debe tener conocimientos de los principios básicos de higiene y sanidad, teniendo claros los peligros que pueden contaminar el producto."
                },
                {
                  "punto": "Evitar el uso de recipientes de vidrio o pequeños objetos metálicos cerca de los cultivos, para evitar la presencia en el producto final de restos de vidrio o de dichos objetos metálicos."
                },
                {
                  "punto": "Si es necesario el uso de utensilios u objetos pequeños, se recomienda tenerlos numerados o identificados adecuadamente."
                }
              ]
            },
            {
              "clase": "imagen",
              "imagen": "img/modFru/manzano.jpg"
            }
          ]
        },
        {
          "clase": "texto",
          "texto": "Un factor a tener en cuenta es la necesidad de tener cierta destreza tanto en el momento de la recolección como en las manipulaciones posteriores, para evitar golpes, magulladuras, desgarros, rasguños o cortes indeseables que, además de afectar negativamente a la calidad estética del producto, pueden suponer una vía de acceso para los microorganismos."
        }
      ]
    },
    {
      "titulo": "Contaminación de origen: Física",
      "contenido": [
        {
          "clase": "texto",
          "texto": "En general, los peligros más importantes en productos del Sector Frutas, Verduras y Derivados son los contaminantes físicos, químicos y biológicos, destacando principalmente los dos últimos."
        },
        {
          "clase": "listaObjetos",
          "contenido": [
            {
              "clase": "texto",
              "texto": "<b>Contaminación física:</b> En origen frutas y verduras pueden traer consigo tierra, piedras, trozos de plástico, astillas de madera, etc. que serán eliminados posteriormente."
            },
            {
              "clase": "imagen",
              "imagen": "img/modFru/zanahorias.jpg",
              "ancho": 300
            }
          ]
        },
        {
          "clase": "imagen",
          "subclase": "ajustarAncho",
          "animacion": "fadeInUp",
          "imagen": "img/mod3/nutrientes.svg"
        },
        {
          "clase": "icono",
          "subclase": "sabiasQue",
          "texto": "<b>¿Sabías qué...</b><br>el coco se llama así porque en portugués coco se llamaba a los fantasmas que asustan a los niños y cuando la expedición de Vasco da Gama llegó a India en 1500, los tripulantes compararon la cáscara y sus tres agujeros con una cabeza con ojos y boca, como las que se usaban para fabricar los fantasmas infantiles?"
        }
      ]
    },
    {
      "titulo": "Contaminación de origen: Química",
      "contenido": [
        {
          "clase": "listaObjetos",
          "contenido": [
            {
              "clase": "listaObjetos",
              "subclase": "columna",
              "contenido": [
                {
                  "clase": "texto",
                  "texto": "<b>Contaminación química:</b> frutas y hortalizas están expuestas a distintos contaminantes químicos que pueden provenir de diferentes fuentes:<br>actividades industriales, actividades humanas (fertilizantes, aplicación de plaguicidas, etc). Destacando los siguientes contaminantes químicos:"
                },
                {
                  "clase": "acordeonSub",
                  "contenido": [
                    {
                      "titulo": "Metales pesados",
                      "contenido": [
                        {
                          "titulo": "Plomo",
                          "texto": "Plomo (Pb): las emisiones más importantes de plomo a la atmósfera proceden de la combustión de gasolinas y de las industrias (hierro y acero, fundiciones de plomo). La vía de entrada en la cadena alimentaria es a través de la deposición atmosférica de plomo en los vegetales."
                        },
                        {
                          "titulo": "Cadmio",
                          "texto": "Cadmio (Cd):  se obtiene como subproducto en la minería o de procedencia industrial. Las plantas pueden absorber el cadmio rápidamente desde el suelo (influyendo su concentración y el pH del suelo)."
                        },
                        {
                          "titulo": "Arsénico",
                          "texto": "Arsénico (As): es un contaminante presente en la naturaleza y también generado por la industria. Antiguamente se empleaba en pesticidas, estando, hoy en día,  prohibida su utilización. Puede presentarse en dos formas: la orgánica y la inorgánica (más tóxica). Las verduras y cereales (como el arroz) lo absorben del suelo o el agua."
                        }
                      ]
                    },
                    {
                      "titulo": "Otros productos químicos",
                      "contenido": [
                        {
                          "titulo": "Pesticidas",
                          "texto": "Son compuestos químicos que se añaden a los cultivos para protegerlos frente a plagas y enfermedades. Son productos muy controlados por la ley y existen unos Límites Máximos de Residuos que son los niveles máximos permitidos legalmente, por debajo de los cuales se considera que el alimento es toxicológicamente aceptable."
                        },
                        {
                          "titulo": "Nitratos",
                          "texto": "Son uno de los componentes principales de fertilizantes y abonos. Permiten a las plantas crecer más rápido, pero si se usan en exceso no son metabolizados y terminan en las hojas de las verduras."
                        },
                        {
                          "titulo": "Tóxicos naturales",
                          "texto": "Son aquellos, sin tener en cuenta los compuestos químicos, que se encuentran presentes de forma natural en la composición del producto. Por ejemplo: setas venenosas.",
                          "imagen": "img/modFru/agarico.jpg",
                          "ancho": 200
                        }
                      ]
                    }
                  ]
                }
              ]
            },
            {
              "clase": "imagen",
              "imagen": "img/modFru/contaminacionq.png"
            }
          ]
        },
        {
          "clase": "icono",
          "subclase": "sabiasQue",
          "texto": "<b>¿Sabías que…</b><br>se recomienda, por precaución, no incluir espinacas ni acelgas en la dieta de niños menores de un año (o en caso de incluirlas que su contenido no supere el 20% del puré) debido al contenido en nitrato de esos vegetales? (Y no dar más de una ración al día a niños entre 1 y 3 años)."
        }
      ]
    },
    {
      "titulo": "Contaminación de origen: Biológica",
      "fondo": "img/modFru/campo.jpg",
      "contenido": [
        {
          "clase": "texto",
          "subclase": "recuadro",
          "opacidad": 0.8,
          "texto": "<b>Contaminación biológica:</b><br>La mayoría de las frutas poseen contaminación superficial procedente de las zonas de cultivo y del ambiente en general (insectos, aves, agua de lluvia…).<br>Por otro lado las <b>hortalizas</b> son alimentos que habitualmente presentan una elevada carga microbiológica ya que se  cultivan directamente en los suelos y algunos microorganismos peligrosos pueden formar parte de la flora natural del suelo o del ambiente (como es el caso del: Clostridium botulinum). No obstante, la vía principal de contaminación se debe al agua de riego que puede aportar microorganismos en caso de encontrarse contaminada.<br>Si además llegan a estar en contacto con materia fecal (por ejemplo, abonos o agua de riego contaminada fecalmente), pueden ser origen de procesos de infecciones de origen alimentario, por microorganismos patógenos que son habituales en el intestino de animales y/o humanos. Esto se debe, por un lado, a unas prácticas incorrectas en la producción al permitir dicha contaminación  y, por otro lado, al hecho de ser productos que se consumen en crudo (no es necesario someterlos a ningún tratamiento previo que elimine los posibles patógenos.<br>Frutas y hortalizas pueden transportar virus (como el de la hepatitis A), bacterias (Salmonella, Escherichia, Shigella, …) parásitos y hongos generadores de micotoxinas."
        },
        {
          "clase": "icono",
          "subclase": "exclamacion",
          "opacidad": 0.8,
          "texto": "<b>RECUERDA:</b><br>De cara al cliente, es importante resaltar que un lavado correcto de frutas y vegetales, antes de su consumo, conllevará la eliminación de contaminantes físicos como tierra o arena, minimizará la presencia de contaminantes químicos como posibles restos de pesticidas y de contaminantes biológicos."
        }
      ]
    },
    {
      "titulo": "Factores: Nutrientes",
      "contenido": [
        {
          "clase": "texto",
          "animacion": "fadeInDown",
          "texto": "<b>Nutrientes</b><br>Además del contenido en agua, para el desarrollo de las bacterias en un alimento influye enormemente la <b>composición</b> del mismo. Las bacterias prefieren alimentos con un alto contenido en proteínas y sustancias nutritivas, como la carne y productos cárnicos cocinados, salsas, cremas, huevos y ovoproductos o productos lácteos. Estos alimentos ricos en proteínas y sustancias nutritivas y agua son los denominados <b>alimentos de alto riesgo</b>. Los alimentos con gran concentración de azúcar, sales, ácidos u otros conservantes no permiten el crecimiento bacteriano y serían por tanto <b>alimentos de bajo riesgo</b>."
        },
        {
          "clase": "imagen",
          "subclase": "ajustarAncho",
          "animacion": "fadeInUp",
          "imagen": "img/mod3/nutrientes.svg"
        }
      ]
    },
    {
      "titulo": "Medidas preventivas",
      "contenido": [
        {
          "clase": "lista",
          "titulo": "Las medidas preventivas para evitar o minimizar la contaminación de origen se basan en unas buenas prácticas higiénico-sanitarias en la producción primaria, especialmente en los siguientes puntos:",
          "contenido": [
            {
              "punto": "Para prevenir la contaminación química, no cultivar en zonas que puedan suponer un foco de contaminación (cerca de fábricas, aguas residuales, etc.). Respecto al uso de pesticidas, sólo se podrán utilizar aquellos productos que estén autorizados para su uso en el cultivo correspondiente, respetando siempre dosis y el plazo de seguridad establecido. Deben ser aplicados por personal formado y capacitado."
            },
            {
              "punto": "Para prevenir la contaminación biológica, se ha de utilizar agua de riego libre de contaminación (se ha de evaluar, por tanto, la procedencia del agua y el tipo de riego empleado) y los abonos deben sufrir un proceso de compostaje en el que se alcanza una temperatura elevada capaz de eliminar a los microorganismos patógenos."
            }
          ]
        },
        {
          "clase": "icono",
          "subclase": "definicion",
          "texto": "<b>Compostaje:</b><br>Consiste en la degradación de la materia orgánica mediante su oxidación y la acción de diversos microorganismos presentes en los propios residuos."
        }
      ]
    },
    {
      "titulo": "SCO 19 Recolección",
      "contenido": [
        {
          "clase": "lista",
          "titulo": "En esta etapa puede producirse contaminación de los alimentos debido a  unas malas prácticas higiénicas en la manipulación de frutas y verduras. Para evitar esto:",
          "contenido": [
            {
              "punto": "El personal debe tener conocimientos de los principios básicos de higiene y sanidad, teniendo claros los peligros que pueden contaminar el producto."
            },
            {
              "punto": "Evitar el uso de recipientes de vidrio o pequeños objetos metálicos cerca de los cultivos, para evitar la presencia en el producto final de restos de vidrio o de dichos objetos metálicos."
            },
            {
              "punto": "Si es necesario el uso de utensilios u objetos pequeños, se recomienda tenerlos numerados o identificados adecuadamente."
            }
          ]
        },
        {
          "clase": "texto",
          "texto": "Un factor a tener en cuenta es la necesidad de tener cierta destreza tanto en el momento de la recolección como en las manipulaciones posteriores, para evitar golpes, magulladuras, desgarros, rasguños o cortes indeseables que, además de afectar negativamente a la calidad estética del producto, pueden suponer una vía de acceso para los microorganismos."
        }
      ]
    },
    {
      "titulo": "Transporte y almacenamiento",
      "contenido": [
        {
          "clase": "lista",
          "titulo": "Estas etapas tienen en común el uso de instalaciones, superficies, equipos, utensilios, recipientes, envases y/o medios de transporte, que entran en contacto directo con frutas y hortalizas frescas, existiendo el peligro de contaminaciones:",
          "contenido": [
            {
              "punto": "Física: incorporación de objetos extraños provenientes de restos de embalajes o de la maquinaria utilizada (por ejemplo: tornillos)."
            },
            {
              "punto": "Química: por la presencia de productos químicos que no deben estar en contacto con los alimentos o por restos de detergentes o desinfectantes presentes en los equipos, superficies, etc. en contacto con ellos."
            },
            {
              "punto": "Biológica: al utilizar equipos, instalaciones, etc. sucias o en estado incorrecto de limpieza y desinfección. Prácticas incorrectas de manipulación que causen golpes, aplastamientos, cortes, etc. con lo que se facilita el acceso a microorganismos. Contaminación cruzada al almacenar/transportar las frutas y hortalizas mezcladas entre sí o junto a otros productos crudos."
            }
          ]
        },
        {
          "clase": "texto",
          "texto": "También hay que tener en cuenta que un almacenamiento prolongado favorecerá la multiplicación de bacterias y mohos, por lo que se hace necesario un buen control en el almacenamiento."
        },
        {
          "clase": "lista",
          "titulo": "<b>Medidas preventivas</b>",
          "contenido": [
            {
              "punto": "Cargar y descargar de forma cuidadosa."
            },
            {
              "punto": "Proteger la mercancía durante el traslado, evitando que los productos se recalienten y pierdan agua."
            },
            {
              "punto": "Mantener las condiciones de temperatura, humedad relativa y circulación de aire constantes para aquellos productos que lo requieran."
            },
            {
              "punto": "Utilizar cajas de un solo uso (cartón, madera o similar) o en caso de ser reutilizables, de materiales fáciles de lavar y desinfectar (descartándose la madera en este caso)."
            },
            {
              "punto": "Controlar las medidas higiénicas de los vehículos de transporte y almacenes."
            },
            {
              "punto": "No transportar ni almacenar frutas y hortalizas junto a otros alimentos o productos químicos que puedan contaminarlos."
            },
            {
              "punto": "Mantener un control y rotación adecuados de los productos almacenados."
            }
          ]
        },
        {
          "clase": "texto",
          "texto": "La refrigeración es recomendable para almacenar algunas frutas y hortalizas frescas, ya que retrasa la maduración, el reblandecimiento y el cambio de textura y color. Además evita la pérdida de humedad y el deterioro por invasión de bacterias y hongos."
        },
        {
          "clase": "texto",
          "texto": "Las condiciones de almacenamiento dependerán del tipo de producto, ya que existen frutas y hortalizas sensibles al frío (oscurecimiento, alteraciones…), a la humedad (por ejemplo: aparición de raíces) y al etileno."
        }
      ]
    },
    {
      "titulo": "Frutas y hortalizas destinadas a Frutería",
      "contenido": [
        {
          "clase": "lista",
          "contenido": [
            {
              "punto": "En el punto de venta al público de frutas y hortalizas frescas, los productos deben clasificarse y presentarse ordenados, separando aquellos productos que puedan transmitir al resto olores o sabores extraños (cebollas, ajos, …)."
            },
            {
              "punto": "Se deben retirar aquellas piezas que presenten signos de deterioro o podredumbre a un lugar adecuado."
            },
            {
              "punto": "Si se trata de autoservicio, se deben proporcionar los medios adecuados (guantes de un solo uso y bolsas de plástico) para una manipulación higiénica de los productos por el público. En otro caso no debe permitirse el contacto directo por el público."
            },
            {
              "punto": "Todos los productos se depositarán sobre estanterías, vitrinas, o cualquier otro medio de exposición que impida el contacto directo de los alimentos con el suelo, y toda superficie o material que entre en contacto con el producto será fácil de limpiar y desinfectar."
            },
            {
              "punto": "Los productos de cuarta gama, que necesitan frío para su conservación, se expondrán en vitrinas o expositores que mantengan temperaturas de refrigeración."
            }
          ]
        }
      ]
    },
    {
      "titulo": "Frutas y hortalizas destinadas a Industria",
      "contenido": [
        {
          "clase": "texto",
          "texto": "Sin entrar en mayor detalle, las frutas y hortalizas cuyo destino sea la Industria Procesadora serán sometidos a diversas operaciones previas, pasando por una o más etapas de procesado hasta la obtención del producto final: congelados, productos de IV gama o conservas."
        },
        {
          "clase": "texto",
          "texto": "Entre estas operaciones previas están aquellas destinadas al acondicionamiento, como pueden ser lavado, pelado, troceado, etc.<br><br>En estas etapas de acondicionamiento, frutas y verduras pueden contaminarse debido a una falta de limpieza y desinfección de equipos y utensilios o por manipulaciones poco higiénicas del personal. Además hay que tener en cuenta que el pelado favorece el acceso a los microorganismos y el cortado incrementa el área expuesta."
        },
        {
          "clase": "texto",
          "texto": "Posteriormente se realizará un procesado específico según el producto final a conseguir. En cada una de estas etapas existen peligros de contaminación física, química y biológica a los que además se puede añadir la multiplicación microbiológica, por lo que las medidas preventivas estarán enfocadas en la prevención de dicha contaminación y a impedir la multiplicación microbiológica.<br><br>En el caso de las conservas, se someterán a un proceso de eliminación de microorganismos (esterilización)."
        }
      ]
    },
    {
      "titulo": "IR REPARTIENDO POR EL MÓDULO",
      "contenido": [
        {
          "clase": "icono",
          "subclase": "sabiasQue",
          "texto": "<b>¿Sabías qué...</b><br>por su alto contenido de ácido, el limón es capaz de matar bacterias y por este motivo, representa un excelente desinfectante natural?"
        },
        {
          "clase": "icono",
          "subclase": "sabiasQue",
          "texto": "<b>¿Sabías qué...</b><br>las manzanas flotan en el agua porque están constituidas en un 25% por aire?"
        },
        {
          "clase": "icono",
          "subclase": "sabiasQue",
          "texto": "<b>¿Sabías qué...</b><br>la fresa es la única fruta que tiene las semillas en su exterior, pudiendo llegar a tener hasta 200?"
        }

      ]
    },
    {
      "titulo": "Despedida",
      "fondo": "img/modFru/grapes.jpg",
      "contenido": [
        {
          "clase": "texto",
          "subclase": "recuadro",
          "animacion": "fadeInRight",
          "texto": "<p>Con este módulo se cierra la formación de manipuladores  de alimentos. Esperamos que lo hayas encontrado instructivo a la par que entretenido. Cualquier sugerencia o mejora que te parezca oportuna para mejorar el curso será bienvenida.</p><br><p>¡Acuérdate de cumplimentar el cuestionario del curso para que podamos evaluar todo lo que has aprendido! ¡Muchas gracias!</p>"
        }
      ]
    },
    {
      "titulo": "Contraportada",
      "fondo": "img/comunes/contraportada.svg",
      "subclase": "portada"
    }
  ]
}
